{
  "films": [
    {
      "name": ".45",
      "genre": "Black comedy",
      "directed_by": "Gary Lennon",
      "initial_release_date": "2006-11-30"
    },
    {
      "name": "9",
      "genre": "Computer Animation",
      "directed_by": "Shane Acker",
      "initial_release_date": "2005-04-21"
    },
    {
      "name": "300",
      "genre": "Epic film",
      "directed_by": "Zack Snyder",
      "initial_release_date": "2006-12-09"
    },
    {
      "name": "¿Quién es el señor López?",
      "genre": "Documentary film",
      "directed_by": "Luis Mandoki"
    },
    {
      "name": "15 Park Avenue",
      "genre": "Art film",
      "directed_by": "Aparna Sen",
      "initial_release_date": "2005-10-27"
    },
    {
      "name": "7G Rainbow Colony",
      "genre": "Drama",
      "directed_by": "Selvaraghavan",
      "initial_release_date": "2004-10-15"
    },
    {
      "name": "3-Iron",
      "genre": "Crime Fiction",
      "directed_by": "Kim Ki-duk",
      "initial_release_date": "2004-09-07"
    },
    {
      "name": "10.5: Apocalypse",
      "genre": "Disaster Film",
      "directed_by": "John Lafia",
      "initial_release_date": "2006-03-18"
    },
    {
      "name": "50 Cent: The New Breed",
      "genre": "Documentary film",
      "directed_by": "Don Robinson",
      "initial_release_date": "2003-04-15"
    },
    {
      "name": "24 Hour Party People",
      "genre": "Biographical film",
      "directed_by": "Michael Winterbottom",
      "initial_release_date": "2002-02-13"
    },
    {
      "name": "25th Hour",
      "genre": "Crime Fiction",
      "directed_by": "Spike Lee",
      "initial_release_date": "2002-12-16"
    },
    {
      "name": "9 Songs",
      "genre": "Erotica",
      "directed_by": "Michael Winterbottom",
      "initial_release_date": "2004-05-16"
    },
    {
      "name": "28 Days",
      "genre": "Comedy-drama",
      "directed_by": "Betty Thomas",
      "initial_release_date": "2000-02-08"
    },
    {
      "name": "10.5",
      "genre": "Disaster Film",
      "directed_by": "John Lafia",
      "initial_release_date": "2004-05-02"
    },
    {
      "name": "7½ Phere",
      "genre": "Bollywood",
      "directed_by": "Ishaan Trivedi",
      "initial_release_date": "2005-07-29"
    },
    {
      "name": "A Beautiful Mind",
      "genre": "Biographical film",
      "directed_by": "Ron Howard",
      "initial_release_date": "2001-12-13"
    },
    {
      "name": "A League of Ordinary Gentlemen",
      "genre": "Documentary film",
      "directed_by": "Christopher Browne",
      "initial_release_date": "2006-03-21"
    },
    {
      "name": "A Man, a Real One",
      "genre": "Comedy",
      "directed_by": "Arnaud Larrieu",
      "initial_release_date": "2003-05-28"
    },
    {
      "name": "A Ring of Endless Light",
      "genre": "Drama",
      "directed_by": "Greg Beeman",
      "initial_release_date": "2002-08-23"
    },
    {
      "name": "A Short Film About John Bolton",
      "genre": "Documentary film",
      "directed_by": "Neil Gaiman"
    },
    {
      "name": "A State of Mind",
      "genre": "Documentary film",
      "directed_by": "Daniel Gordon",
      "initial_release_date": "2005-08-10"
    },
    {
      "name": "A View from Eiffel Tower",
      "genre": "Drama",
      "directed_by": "Nikola Vukčević"
    },
    {
      "name": "A Walk to Remember",
      "genre": "Coming of age",
      "directed_by": "Adam Shankman",
      "initial_release_date": "2002-01-23"
    },
    {
      "name": "a/k/a Tommy Chong",
      "genre": "Documentary film",
      "directed_by": "Josh Gilbert",
      "initial_release_date": "2006-06-14"
    },
    {
      "name": "Aalvar",
      "genre": "Action Film",
      "directed_by": "Chella",
      "initial_release_date": "2007-01-12"
    },
    {
      "name": "Abduction: The Megumi Yokota Story",
      "genre": "Documentary film",
      "directed_by": "Patty Kim"
    },
    {
      "name": "About Schmidt",
      "genre": "Black comedy",
      "directed_by": "Alexander Payne",
      "initial_release_date": "2002-05-22"
    },
    {
      "name": "Adaptation",
      "genre": "Crime Fiction",
      "directed_by": "Spike Jonze",
      "initial_release_date": "2002-12-06"
    },
    {
      "name": "Adrenaline Rush",
      "genre": "Documentary film",
      "directed_by": "Marc Fafard",
      "initial_release_date": "2002-10-18"
    },
    {
      "name": "Essential Keys To Better Bowling",
      "genre": "Documentary film"
    },
    {
      "name": "Adventures Into Digital Comics",
      "genre": "Documentary film",
      "directed_by": "Sébastien Dumesnil"
    },
    {
      "name": "Aethirree",
      "genre": "Comedy",
      "directed_by": "K. S. Ravikumar",
      "initial_release_date": "2004-04-23"
    },
    {
      "name": "After Innocence",
      "genre": "Documentary film",
      "directed_by": "Jessica Sanders"
    },
    {
      "name": "After the Sunset",
      "genre": "Crime Fiction",
      "directed_by": "Brett Ratner",
      "initial_release_date": "2004-11-10"
    },
    {
      "name": "Aftermath",
      "genre": "Crime Fiction",
      "directed_by": "Thomas Farone",
      "initial_release_date": "2013-03-01"
    },
    {
      "name": "Against the Ropes",
      "genre": "Biographical film",
      "directed_by": "Charles S. Dutton",
      "initial_release_date": "2004-02-20"
    },
    {
      "name": "Agent Cody Banks 2: Destination London",
      "genre": "Adventure Film",
      "directed_by": "Kevin Allen",
      "initial_release_date": "2004-03-12"
    },
    {
      "name": "Agent One-Half",
      "genre": "Comedy",
      "directed_by": "Brian Bero"
    },
    {
      "name": "Agnes and His Brothers",
      "genre": "Drama",
      "directed_by": "Oskar Roehler",
      "initial_release_date": "2004-09-05"
    },
    {
      "name": "Aileen: Life and Death of a Serial Killer",
      "genre": "Documentary film",
      "directed_by": "Nick Broomfield",
      "initial_release_date": "2003-05-10"
    },
    {
      "name": "Jodhaa Akbar",
      "genre": "Biographical film",
      "directed_by": "Ashutosh Gowariker",
      "initial_release_date": "2008-02-13"
    },
    {
      "name": "Akeelah and the Bee",
      "genre": "Drama",
      "directed_by": "Doug Atchison",
      "initial_release_date": "2006-03-16"
    },
    {
      "name": "Ali",
      "genre": "Biographical film",
      "directed_by": "Michael Mann",
      "initial_release_date": "2001-12-11"
    },
    {
      "name": "Aliens of the Deep",
      "genre": "Documentary film",
      "directed_by": "James Cameron",
      "initial_release_date": "2005-01-28"
    },
    {
      "name": "All About Lily Chou-Chou",
      "genre": "Crime Fiction",
      "directed_by": "Shunji Iwai",
      "initial_release_date": "2001-09-07"
    },
    {
      "name": "All About the Benjamins",
      "genre": "Action Film",
      "directed_by": "Kevin Bray",
      "initial_release_date": "2002-03-08"
    },
    {
      "name": "Allari Bullodu",
      "genre": "Comedy",
      "directed_by": "Kovelamudi Raghavendra Rao"
    },
    {
      "name": "Allari Pidugu",
      "genre": "Drama",
      "directed_by": "Jayant Paranji",
      "initial_release_date": "2005-10-05"
    },
    {
      "name": "Alles auf Zucker!",
      "genre": "Comedy",
      "directed_by": "Dani Levy",
      "initial_release_date": "2004-12-31"
    },
    {
      "name": "Alone and Restless",
      "genre": "Drama",
      "directed_by": "Michael Thomas Dunn"
    },
    {
      "name": "Alpha Dog",
      "genre": "Crime Fiction",
      "directed_by": "Nick Cassavetes",
      "initial_release_date": "2006-01-27"
    },
    {
      "name": "America: Freedom to Fascism",
      "genre": "Documentary film",
      "directed_by": "Aaron Russo",
      "initial_release_date": "2006-07-28"
    },
    {
      "name": "American Cowslip",
      "genre": "Black comedy",
      "directed_by": "Mark David",
      "initial_release_date": "2009-07-24"
    },
    {
      "name": "American Gangster",
      "genre": "Crime Fiction",
      "directed_by": "Ridley Scott",
      "initial_release_date": "2007-10-19"
    },
    {
      "name": "American Pie Presents: The Naked Mile",
      "genre": "Comedy",
      "directed_by": "Joe Nussbaum",
      "initial_release_date": "2006-12-07"
    },
    {
      "name": "American Pie Presents: Band Camp",
      "genre": "Comedy",
      "directed_by": "Steve Rash",
      "initial_release_date": "2005-10-31"
    },
    {
      "name": "American Psycho",
      "genre": "Black comedy",
      "directed_by": "Mary Harron",
      "initial_release_date": "2000-01-21"
    },
    {
      "name": "Amrutham",
      "genre": "Drama",
      "directed_by": "Sibi Malayil",
      "initial_release_date": "2004-12-24"
    },
    {
      "name": "An American Crime",
      "genre": "Crime Fiction",
      "directed_by": "Tommy O'Haver",
      "initial_release_date": "2007-01-19"
    },
    {
      "name": "An Evening with Kevin Smith",
      "genre": "Documentary film",
      "directed_by": "J.M. Kenny"
    },
    {
      "name": "An Evening with Kevin Smith 2: Evening Harder",
      "genre": "Documentary film",
      "directed_by": "J.M. Kenny"
    },
    {
      "name": "An Everlasting Piece",
      "genre": "Comedy",
      "directed_by": "Barry Levinson",
      "initial_release_date": "2000-12-25"
    },
    {
      "name": "An Extremely Goofy Movie",
      "genre": "Animation",
      "directed_by": "Ian Harrowell",
      "initial_release_date": "2000-02-29"
    },
    {
      "name": "An Inconvenient Truth",
      "genre": "Documentary film",
      "directed_by": "Davis Guggenheim",
      "initial_release_date": "2006-01-24"
    },
    {
      "name": "Analyze That",
      "genre": "Buddy film",
      "directed_by": "Harold Ramis",
      "initial_release_date": "2002-12-06"
    },
    {
      "name": "Anchorman: The Legend of Ron Burgundy",
      "genre": "Comedy",
      "directed_by": "Adam McKay",
      "initial_release_date": "2004-06-28"
    },
    {
      "name": "Andarivaadu",
      "genre": "Comedy",
      "directed_by": "Srinu Vaitla",
      "initial_release_date": "2005-06-03"
    },
    {
      "name": "Andhrawala",
      "genre": "Adventure Film",
      "directed_by": "Puri Jagannadh",
      "initial_release_date": "2004-01-01"
    },
    {
      "name": "Ang Tanging Ina",
      "genre": "Comedy",
      "directed_by": "Wenn V. Deramas",
      "initial_release_date": "2003-05-28"
    },
    {
      "name": "Anger Management",
      "genre": "Black comedy",
      "directed_by": "Peter Segal",
      "initial_release_date": "2003-03-05"
    },
    {
      "name": "Animal Factory",
      "genre": "Crime Fiction",
      "directed_by": "Steve Buscemi",
      "initial_release_date": "2000-10-22"
    },
    {
      "name": "Anus Magillicutty",
      "genre": "B movie",
      "directed_by": "Morey Fineburgh",
      "initial_release_date": "2003-04-15"
    },
    {
      "name": "Any Way the Wind Blows",
      "genre": "Comedy-drama",
      "directed_by": "Tom Barman",
      "initial_release_date": "2003-05-17"
    },
    {
      "name": "Apocalypto",
      "genre": "Action Film",
      "directed_by": "Mel Gibson",
      "initial_release_date": "2006-12-08"
    },
    {
      "name": "Aquamarine",
      "genre": "Coming of age",
      "directed_by": "Elizabeth Allen Rosenbaum",
      "initial_release_date": "2006-02-26"
    },
    {
      "name": "Arahan",
      "genre": "Action Film",
      "directed_by": "Ryoo Seung-wan",
      "initial_release_date": "2004-04-30"
    },
    {
      "name": "Arinthum Ariyamalum",
      "genre": "Crime Fiction",
      "directed_by": "Vishnuvardhan",
      "initial_release_date": "2005-05-20"
    },
    {
      "name": "Arisan!",
      "genre": "Comedy",
      "directed_by": "Nia Dinata",
      "initial_release_date": "2003-12-10"
    },
    {
      "name": "Arjun",
      "genre": "Action Film",
      "directed_by": "Gunasekhar",
      "initial_release_date": "2004-08-18"
    },
    {
      "name": "Around the World in 80 Days",
      "genre": "Adventure Film",
      "directed_by": "Frank Coraci",
      "initial_release_date": "2004-06-13"
    },
    {
      "name": "Art School Confidential",
      "genre": "Comedy-drama",
      "directed_by": "Terry Zwigoff"
    },
    {
      "name": "Aryan: Unbreakable",
      "genre": "Action Film",
      "directed_by": "Abhishek Kapoor",
      "initial_release_date": "2006-12-05"
    },
    {
      "name": "Ashok",
      "genre": "Action Film",
      "directed_by": "Surender Reddy",
      "initial_release_date": "2006-07-13"
    },
    {
      "name": "Ashoka the Great",
      "genre": "Action Film",
      "directed_by": "Santosh Sivan",
      "initial_release_date": "2001-09-13"
    },
    {
      "name": "Astitva",
      "genre": "Art film",
      "directed_by": "Mahesh Manjrekar",
      "initial_release_date": "2000-10-06"
    },
    {
      "name": "Athadu",
      "genre": "Action Film",
      "directed_by": "Trivikram Srinivas",
      "initial_release_date": "2005-08-10"
    },
    {
      "name": "ATL",
      "genre": "Coming of age",
      "directed_by": "Chris Robinson",
      "initial_release_date": "2006-03-28"
    },
    {
      "name": "Atlantis: The Lost Empire",
      "genre": "Adventure Film",
      "directed_by": "Gary Trousdale",
      "initial_release_date": "2001-06-03"
    },
    {
      "name": "Attahasam",
      "genre": "Action Film",
      "directed_by": "Saran",
      "initial_release_date": "2004-11-12"
    },
    {
      "name": "Attila",
      "genre": "Adventure Film",
      "directed_by": "Dick Lowry"
    },
    {
      "name": "Austin Powers: Goldmember",
      "genre": "Action Film",
      "directed_by": "Jay Roach",
      "initial_release_date": "2002-07-22"
    },
    {
      "name": "Australian Rules",
      "genre": "Drama",
      "directed_by": "Paul Goldman"
    },
    {
      "name": "Oram Po",
      "genre": "Action Film",
      "directed_by": "Pushkar",
      "initial_release_date": "2007-02-16"
    },
    {
      "name": "Auto Focus",
      "genre": "Biographical film",
      "directed_by": "Paul Schrader",
      "initial_release_date": "2002-09-08"
    },
    {
      "name": "Avenging Angelo",
      "genre": "Action Film",
      "directed_by": "Martyn Burke",
      "initial_release_date": "2002-08-30"
    },
    {
      "name": "Awara Paagal Deewana",
      "genre": "Action Film",
      "directed_by": "Vikram Bhatt",
      "initial_release_date": "2002-06-20"
    },
    {
      "name": "Awesome; I Fuckin' Shot That!",
      "genre": "Concert film",
      "directed_by": "Adam Yauch",
      "initial_release_date": "2006-01-06"
    },
    {
      "name": "Azumi",
      "genre": "Action Film",
      "directed_by": "Ryuhei Kitamura",
      "initial_release_date": "2003-05-10"
    },
    {
      "name": "Baby Boy",
      "genre": "Coming of age",
      "directed_by": "John Singleton",
      "initial_release_date": "2001-06-21"
    },
    {
      "name": "Bad Boys II",
      "genre": "Action Film",
      "directed_by": "Michael Bay",
      "initial_release_date": "2003-07-09"
    },
    {
      "name": "Bad Eggs",
      "genre": "Comedy",
      "directed_by": "Tony Martin"
    },
    {
      "name": "Bad Santa",
      "genre": "Black comedy",
      "directed_by": "Terry Zwigoff",
      "initial_release_date": "2003-11-26"
    },
    {
      "name": "Baghdad ER",
      "genre": "Documentary film",
      "directed_by": "Jon Alpert",
      "initial_release_date": "2006-08-29"
    },
    {
      "name": "Baise Moi",
      "genre": "Erotica",
      "directed_by": "Virginie Despentes",
      "initial_release_date": "2000-06-28"
    },
    {
      "name": "Bala",
      "genre": "Drama",
      "directed_by": "Deepak",
      "initial_release_date": "2002-12-13"
    },
    {
      "name": "Bambi II",
      "genre": "Animation",
      "directed_by": "Brian Pimental",
      "initial_release_date": "2006-01-26"
    },
    {
      "name": "Bangaram",
      "genre": "Action Film",
      "directed_by": "Dharani",
      "initial_release_date": "2006-05-03"
    },
    {
      "name": "Barbershop",
      "genre": "Ensemble Film",
      "directed_by": "Tim Story",
      "initial_release_date": "2002-08-07"
    },
    {
      "name": "Basic emotions",
      "genre": "Drama",
      "directed_by": "Thomas Moon",
      "initial_release_date": "2004-09-09"
    },
    {
      "name": "Battle In Heaven",
      "genre": "Drama",
      "directed_by": "Carlos Reygadas",
      "initial_release_date": "2005-05-15"
    },
    {
      "name": "Batman Begins",
      "genre": "Action Film",
      "directed_by": "Christopher Nolan",
      "initial_release_date": "2005-06-10"
    },
    {
      "name": "Batman: Mystery of the Batwoman",
      "genre": "Animated cartoon",
      "directed_by": "Curt Geda",
      "initial_release_date": "2003-10-21"
    },
    {
      "name": "BBS: The Documentary",
      "genre": "Documentary film",
      "directed_by": "Jason Scott Sadofsky"
    },
    {
      "name": "Be Cool",
      "genre": "Crime Fiction",
      "directed_by": "F. Gary Gray",
      "initial_release_date": "2005-03-04"
    },
    {
      "name": "Beah: A Black Woman Speaks",
      "genre": "Documentary film",
      "directed_by": "Lisa Gay Hamilton",
      "initial_release_date": "2003-08-22"
    },
    {
      "name": "Beauty Shop",
      "genre": "Comedy",
      "directed_by": "Bille Woodruff",
      "initial_release_date": "2005-03-24"
    },
    {
      "name": "Beerfest",
      "genre": "Absurdism",
      "directed_by": "Jay Chandrasekhar",
      "initial_release_date": "2006-08-25"
    },
    {
      "name": "Behind the Mask",
      "genre": "Documentary film",
      "directed_by": "Shannon Keith",
      "initial_release_date": "2006-03-21"
    },
    {
      "name": "Behind the Sun",
      "genre": "Drama",
      "directed_by": "Walter Salles",
      "initial_release_date": "2001-09-06"
    },
    {
      "name": "Bekhal's Tears",
      "genre": "Drama",
      "directed_by": "Lauand Omar"
    },
    {
      "name": "Belly of the Beast",
      "genre": "Action Film",
      "directed_by": "Ching Siu-tung",
      "initial_release_date": "2003-12-30"
    },
    {
      "name": "Bend It Like Beckham",
      "genre": "Coming of age",
      "directed_by": "Gurinder Chadha",
      "initial_release_date": "2002-04-11"
    },
    {
      "name": "Beowulf",
      "genre": "Adventure Film",
      "directed_by": "Robert Zemeckis",
      "initial_release_date": "2007-11-05"
    },
    {
      "name": "Beowulf &amp; Grendel",
      "genre": "Adventure Film",
      "directed_by": "Sturla Gunnarsson",
      "initial_release_date": "2005-09-14"
    },
    {
      "name": "Best in Show",
      "genre": "Comedy",
      "directed_by": "Christopher Guest",
      "initial_release_date": "2000-09-08"
    },
    {
      "name": "Better Luck Tomorrow",
      "genre": "Coming of age",
      "directed_by": "Justin Lin",
      "initial_release_date": "2003-04-11"
    },
    {
      "name": "Bettie Page: Dark Angel",
      "genre": "Biographical film",
      "directed_by": "Nico B.",
      "initial_release_date": "2004-02-11"
    },
    {
      "name": "Beyond Borders",
      "genre": "Adventure Film",
      "directed_by": "Martin Campbell",
      "initial_release_date": "2003-10-24"
    },
    {
      "name": "Bhadra",
      "genre": "Action Film",
      "directed_by": "Boyapati Srinu",
      "initial_release_date": "2005-05-12"
    },
    {
      "name": "Bhageeratha",
      "genre": "Drama",
      "directed_by": "Rasool Ellore",
      "initial_release_date": "2005-10-13"
    },
    {
      "name": "Bheemaa",
      "genre": "Action Film",
      "directed_by": "N. Lingusamy",
      "initial_release_date": "2008-01-14"
    },
    {
      "name": "Big Man, Little Love",
      "genre": "Drama",
      "directed_by": "Handan İpekçi",
      "initial_release_date": "2001-10-19"
    },
    {
      "name": "Big Momma's House",
      "genre": "Action Film",
      "directed_by": "Raja Gosnell",
      "initial_release_date": "2000-05-31"
    },
    {
      "name": "Big Momma's House 2",
      "genre": "Crime Fiction",
      "directed_by": "John Whitesell",
      "initial_release_date": "2006-01-26"
    },
    {
      "name": "Big Trouble",
      "genre": "Crime Fiction",
      "directed_by": "Barry Sonnenfeld",
      "initial_release_date": "2002-04-05"
    },
    {
      "name": "Biggie &amp; Tupac",
      "genre": "Documentary film",
      "directed_by": "Nick Broomfield",
      "initial_release_date": "2002-01-11"
    },
    {
      "name": "Billy Elliot",
      "genre": "Comedy",
      "directed_by": "Stephen Daldry",
      "initial_release_date": "2000-05-19"
    },
    {
      "name": "Birthday Girl",
      "genre": "Black comedy",
      "directed_by": "Jez Butterworth",
      "initial_release_date": "2002-02-01"
    },
    {
      "name": "Bite Me, Fanboy",
      "genre": "Comedy",
      "directed_by": "Mat Nastos",
      "initial_release_date": "2005-06-01"
    },
    {
      "name": "Black Friday",
      "genre": "Crime Fiction",
      "directed_by": "Anurag Kashyap",
      "initial_release_date": "2004-05-20"
    },
    {
      "name": "Bleach: Memories of Nobody",
      "genre": "Anime",
      "directed_by": "Noriyuki Abe",
      "initial_release_date": "2006-12-16"
    },
    {
      "name": "Blind Shaft",
      "genre": "Crime Fiction",
      "directed_by": "Li Yang",
      "initial_release_date": "2003-02-12"
    },
    {
      "name": "Blissfully Yours",
      "genre": "Erotica",
      "directed_by": "Apichatpong Weerasethakul",
      "initial_release_date": "2002-05-17"
    },
    {
      "name": "Blood of a Champion",
      "genre": "Crime Fiction",
      "directed_by": "Lawrence Page",
      "initial_release_date": "2006-03-07"
    },
    {
      "name": "Bloodsport - ECW's Most Violent Matches",
      "genre": "Documentary film",
      "initial_release_date": "2006-02-07"
    },
    {
      "name": "Blow",
      "genre": "Biographical film",
      "directed_by": "Ted Demme",
      "initial_release_date": "2001-03-29"
    },
    {
      "name": "Blue Collar Comedy Tour Rides Again",
      "genre": "Documentary film",
      "directed_by": "C. B. Harding",
      "initial_release_date": "2004-12-05"
    },
    {
      "name": "Boiler Room",
      "genre": "Crime Fiction",
      "directed_by": "Ben Younger",
      "initial_release_date": "2000-01-30"
    },
    {
      "name": "Bollywood/Hollywood",
      "genre": "Bollywood",
      "directed_by": "Deepa Mehta",
      "initial_release_date": "2002-10-25"
    },
    {
      "name": "Bomb the System",
      "genre": "Crime Fiction",
      "directed_by": "Adam Bhala Lough"
    },
    {
      "name": "Bon Cop, Bad Cop",
      "genre": "Crime Fiction",
      "directed_by": "Eric Canuel"
    },
    {
      "name": "Boogiepop and Others",
      "genre": "Animation",
      "directed_by": "Ryu Kaneda",
      "initial_release_date": "2000-03-11"
    },
    {
      "name": "Bimmer",
      "genre": "Crime Fiction",
      "directed_by": "Pyotr Buslov",
      "initial_release_date": "2003-08-02"
    },
    {
      "name": "Borat: Cultural Learnings of America for Make Benefit Glorious Nation of Kazakhstan",
      "genre": "Comedy",
      "directed_by": "Larry Charles",
      "initial_release_date": "2006-08-04"
    },
    {
      "name": "Born into Brothels: Calcutta's Red Light Kids",
      "genre": "Documentary film",
      "directed_by": "Zana Briski",
      "initial_release_date": "2004-01-17"
    },
    {
      "name": "Bowling Fun And Fundamentals For Boys And Girls",
      "genre": "Documentary film"
    },
    {
      "name": "Bring It On",
      "genre": "Comedy",
      "directed_by": "Peyton Reed",
      "initial_release_date": "2000-08-22"
    },
    {
      "name": "Broadway: The Golden Age",
      "genre": "Documentary film",
      "directed_by": "Rick McKay",
      "initial_release_date": "2004-06-11"
    },
    {
      "name": "Brother 2",
      "genre": "Crime Fiction",
      "directed_by": "Aleksei Balabanov",
      "initial_release_date": "2000-05-11"
    },
    {
      "name": "Bruce Almighty",
      "genre": "Comedy",
      "directed_by": "Tom Shadyac",
      "initial_release_date": "2003-05-23"
    },
    {
      "name": "Bubble",
      "genre": "Crime Fiction",
      "directed_by": "Steven Soderbergh",
      "initial_release_date": "2005-09-03"
    },
    {
      "name": "Bus 174",
      "genre": "Documentary film",
      "directed_by": "José Padilha",
      "initial_release_date": "2002-10-22"
    },
    {
      "name": "Bus Conductor",
      "genre": "Comedy",
      "directed_by": "V. M. Vinu",
      "initial_release_date": "2005-12-23"
    },
    {
      "name": "C.I.D.Moosa",
      "genre": "Action Film",
      "directed_by": "Johny Antony",
      "initial_release_date": "2003-07-04"
    },
    {
      "name": "Cabaret Paradis",
      "genre": "Comedy",
      "directed_by": "Corinne Benizio",
      "initial_release_date": "2006-04-12"
    },
    {
      "name": "Cactuses",
      "genre": "Drama",
      "directed_by": "Matt Hannon",
      "initial_release_date": "2006-03-15"
    },
    {
      "name": "Capote",
      "genre": "Crime Fiction",
      "directed_by": "Bennett Miller",
      "initial_release_date": "2005-09-02"
    },
    {
      "name": "Capturing the Friedmans",
      "genre": "Documentary film",
      "directed_by": "Andrew Jarecki",
      "initial_release_date": "2003-01-17"
    },
    {
      "name": "Cars",
      "genre": "Animation",
      "directed_by": "John Lasseter",
      "initial_release_date": "2006-03-14"
    },
    {
      "name": "Cast Away",
      "genre": "Airplanes and airports",
      "directed_by": "Robert Zemeckis",
      "initial_release_date": "2000-12-07"
    },
    {
      "name": "Castlevania",
      "genre": "Action Film",
      "directed_by": "Paul W. S. Anderson"
    },
    {
      "name": "Catch Me If You Can",
      "genre": "Crime Fiction",
      "directed_by": "Steven Spielberg",
      "initial_release_date": "2002-12-16"
    },
    {
      "name": "Caterina in the Big City",
      "genre": "Comedy",
      "directed_by": "Paolo Virzì",
      "initial_release_date": "2003-10-24"
    },
    {
      "name": "Cats &amp; Dogs",
      "genre": "Adventure Film",
      "directed_by": "Lawrence Guterman",
      "initial_release_date": "2001-07-04"
    },
    {
      "name": "Catwoman",
      "genre": "Action Film",
      "directed_by": "Pitof",
      "initial_release_date": "2004-07-19"
    },
    {
      "name": "Chai Lai",
      "genre": "Action Film",
      "directed_by": "Poj Arnon",
      "initial_release_date": "2006-01-26"
    },
    {
      "name": "Chain",
      "genre": "Documentary film",
      "directed_by": "Jem Cohen"
    },
    {
      "name": "Challenger",
      "genre": "Drama",
      "directed_by": "Philip Kaufman"
    },
    {
      "name": "Chandni Bar",
      "genre": "Crime Fiction",
      "directed_by": "Madhur Bhandarkar",
      "initial_release_date": "2001-09-28"
    },
    {
      "name": "Charlie's Angels",
      "genre": "Action Film",
      "directed_by": "Joseph McGinty Nichol",
      "initial_release_date": "2000-10-22"
    },
    {
      "name": "Charlotte's Web",
      "genre": "Animation",
      "directed_by": "Gary Winick",
      "initial_release_date": "2006-12-07"
    },
    {
      "name": "Chasing the Horizon",
      "genre": "Documentary film",
      "directed_by": "Markus Canter",
      "initial_release_date": "2006-04-26"
    },
    {
      "name": "Chathikkatha Chanthu",
      "genre": "Comedy",
      "directed_by": "Meccartin",
      "initial_release_date": "2004-04-14"
    },
    {
      "name": "Chhatrapati",
      "genre": "Action Film",
      "directed_by": "S. S. Rajamouli",
      "initial_release_date": "2005-09-25"
    },
    {
      "name": "Checking Out",
      "genre": "Black comedy",
      "directed_by": "Jeff Hare",
      "initial_release_date": "2005-04-10"
    },
    {
      "name": "Chess",
      "genre": "Crime Fiction",
      "directed_by": "RajBabu",
      "initial_release_date": "2006-07-07"
    },
    {
      "name": "Chicken Little",
      "genre": "Animation",
      "directed_by": "Mark Dindal",
      "initial_release_date": "2005-10-30"
    },
    {
      "name": "Child Marriage",
      "genre": "Documentary film",
      "directed_by": "Neeraj Kumar"
    },
    {
      "name": "Choose Your Own Adventure The Abominable Snowman",
      "genre": "Adventure Film",
      "directed_by": "Bob Doucette",
      "initial_release_date": "2006-07-25"
    },
    {
      "name": "Chopin: Desire for Love",
      "genre": "Biographical film",
      "directed_by": "Jerzy Antczak",
      "initial_release_date": "2002-03-01"
    },
    {
      "name": "Chopper",
      "genre": "Biographical film",
      "directed_by": "Andrew Dominik",
      "initial_release_date": "2000-08-03"
    },
    {
      "name": "Christmas with the Kranks",
      "genre": "Christmas movie",
      "directed_by": "Joe Roth",
      "initial_release_date": "2004-11-24"
    },
    {
      "name": "Chukkallo Chandrudu",
      "genre": "Comedy",
      "directed_by": "Siva Kumar",
      "initial_release_date": "2006-01-14"
    },
    {
      "name": "Cinderella Man",
      "genre": "Biographical film",
      "directed_by": "Ron Howard",
      "initial_release_date": "2005-05-23"
    },
    {
      "name": "Cinemania",
      "genre": "Documentary film",
      "directed_by": "Angela Christlieb"
    },
    {
      "name": "City of God",
      "genre": "Crime Fiction",
      "directed_by": "Fernando Meirelles",
      "initial_release_date": "2002-05-18"
    },
    {
      "name": "Clear Cut: The Story of Philomath, Oregon",
      "genre": "Documentary film",
      "directed_by": "Peter Richardson",
      "initial_release_date": "2006-01-20"
    },
    {
      "name": "Clerks II",
      "genre": "Buddy film",
      "directed_by": "Kevin Smith",
      "initial_release_date": "2006-05-26"
    },
    {
      "name": "Click",
      "genre": "Comedy",
      "directed_by": "Frank Coraci",
      "initial_release_date": "2006-06-22"
    },
    {
      "name": "Coach Carter",
      "genre": "Coming of age",
      "directed_by": "Thomas Carter",
      "initial_release_date": "2005-01-13"
    },
    {
      "name": "The Coast Guard",
      "genre": "Action Film",
      "directed_by": "Kim Ki-duk",
      "initial_release_date": "2002-11-14"
    },
    {
      "name": "Cold Showers",
      "genre": "Coming of age",
      "directed_by": "Antony Cordier",
      "initial_release_date": "2005-05-22"
    },
    {
      "name": "Collateral Damage",
      "genre": "Action Film",
      "directed_by": "Andrew Davis",
      "initial_release_date": "2002-02-04"
    },
    {
      "name": "Coming Out",
      "genre": "Comedy",
      "directed_by": "Joel Zwick"
    },
    {
      "name": "Confessions of a Dangerous Mind",
      "genre": "Biographical film",
      "directed_by": "George Clooney"
    },
    {
      "name": "Control Room",
      "genre": "Documentary film",
      "directed_by": "Jehane Noujaim"
    },
    {
      "name": "Control",
      "genre": "Biographical film",
      "directed_by": "Anton Corbijn",
      "initial_release_date": "2007-05-17"
    },
    {
      "name": "Copying Beethoven",
      "genre": "Biographical film",
      "directed_by": "Agnieszka Holland",
      "initial_release_date": "2006-07-30"
    },
    {
      "name": "Corporate",
      "genre": "Drama",
      "directed_by": "Madhur Bhandarkar",
      "initial_release_date": "2006-07-07"
    },
    {
      "name": "Cowboy Bebop: The Movie",
      "genre": "Anime",
      "directed_by": "Shinichirō Watanabe",
      "initial_release_date": "2001-09-01"
    },
    {
      "name": "Crackerjack",
      "genre": "Comedy",
      "directed_by": "Paul Moloney",
      "initial_release_date": "2002-11-07"
    },
    {
      "name": "Crash",
      "genre": "Crime Fiction",
      "directed_by": "Paul Haggis",
      "initial_release_date": "2004-09-10"
    },
    {
      "name": "Crimson Rivers II: Angels of the Apocalypse",
      "genre": "Action Film",
      "directed_by": "Olivier Dahan",
      "initial_release_date": "2004-02-18"
    },
    {
      "name": "Crocodile Dundee in Los Angeles",
      "genre": "Action Film",
      "directed_by": "Simon Wincer",
      "initial_release_date": "2001-04-12"
    },
    {
      "name": "Crossover",
      "genre": "Action Film",
      "directed_by": "Preston A. Whitmore II",
      "initial_release_date": "2006-09-01"
    },
    {
      "name": "Crossroads",
      "genre": "Coming of age",
      "directed_by": "Tamra Davis",
      "initial_release_date": "2002-02-11"
    },
    {
      "name": "Cruel Intentions 3",
      "genre": "Erotica",
      "directed_by": "Scott Ziehl",
      "initial_release_date": "2004-05-25"
    },
    {
      "name": "Curious George",
      "genre": "Animation",
      "directed_by": "Matthew O'Callaghan",
      "initial_release_date": "2006-02-10"
    },
    {
      "name": "Daisy",
      "genre": "Chinese Movies",
      "directed_by": "Andrew Lau",
      "initial_release_date": "2006-03-09"
    },
    {
      "name": "Daivanamathil",
      "genre": "Drama",
      "directed_by": "Jayaraj"
    },
    {
      "name": "Daltry Calhoun",
      "genre": "Black comedy",
      "directed_by": "Katrina Holden Bronson",
      "initial_release_date": "2005-09-25"
    },
    {
      "name": "Daredevil",
      "genre": "Action Film",
      "directed_by": "Mark Steven Johnson",
      "initial_release_date": "2003-02-09"
    },
    {
      "name": "Dark Blue",
      "genre": "Action Film",
      "directed_by": "Ron Shelton",
      "initial_release_date": "2002-12-14"
    },
    {
      "name": "Darwin's Nightmare",
      "genre": "Documentary film",
      "directed_by": "Hubert Sauper",
      "initial_release_date": "2004-09-01"
    },
    {
      "name": "Dave Chappelle's Block Party",
      "genre": "Documentary film",
      "directed_by": "Michel Gondry",
      "initial_release_date": "2006-03-03"
    },
    {
      "name": "Death in Gaza",
      "genre": "Documentary film",
      "directed_by": "James Miller",
      "initial_release_date": "2004-02-11"
    },
    {
      "name": "Death to Smoochy",
      "genre": "Comedy",
      "directed_by": "Danny DeVito",
      "initial_release_date": "2002-03-29"
    },
    {
      "name": "Death Trance",
      "genre": "Action Film",
      "directed_by": "Yuji Shimomura",
      "initial_release_date": "2005-05-12"
    },
    {
      "name": "December Boys",
      "genre": "Coming of age",
      "directed_by": "Rod Hardy"
    },
    {
      "name": "Dev",
      "genre": "Drama",
      "directed_by": "Govind Nihalani",
      "initial_release_date": "2004-06-11"
    },
    {
      "name": "Devil's Playground",
      "genre": "Documentary film",
      "directed_by": "Lucy Walker",
      "initial_release_date": "2003-02-04"
    },
    {
      "name": "Dhoom 2",
      "genre": "Crime Fiction",
      "directed_by": "Sanjay Gadhvi",
      "initial_release_date": "2006-11-23"
    },
    {
      "name": "Dhyaas Parva",
      "genre": "Biographical film",
      "directed_by": "Amol Palekar"
    },
    {
      "name": "Diary of a Mad Black Woman",
      "genre": "Comedy-drama",
      "directed_by": "Darren Grant",
      "initial_release_date": "2005-02-25"
    },
    {
      "name": "Die Bad",
      "genre": "Crime Fiction",
      "directed_by": "Ryoo Seung-wan",
      "initial_release_date": "2000-07-15"
    },
    {
      "name": "Die Mommie Die!",
      "genre": "Comedy",
      "directed_by": "Mark Rucker",
      "initial_release_date": "2003-01-20"
    },
    {
      "name": "Digimon: The Movie",
      "genre": "Anime",
      "directed_by": "Mamoru Hosoda",
      "initial_release_date": "2000-03-17"
    },
    {
      "name": "Digital Monster X-Evolution",
      "genre": "Computer Animation",
      "directed_by": "Hiroyuki Kakudō",
      "initial_release_date": "2005-01-03"
    },
    {
      "name": "Digna... hasta el último aliento",
      "genre": "Documentary film",
      "directed_by": "Felipe Cazals",
      "initial_release_date": "2004-12-17"
    },
    {
      "name": "Dil Chahta Hai",
      "genre": "Bollywood",
      "directed_by": "Farhan Akhtar",
      "initial_release_date": "2001-07-24"
    },
    {
      "name": "Dinosaur",
      "genre": "Computer Animation",
      "directed_by": "Eric Leighton",
      "initial_release_date": "2000-05-13"
    },
    {
      "name": "Dirty Deeds",
      "genre": "Comedy",
      "directed_by": "David Kendall",
      "initial_release_date": "2005-08-26"
    },
    {
      "name": "Distant Lights",
      "genre": "Drama",
      "directed_by": "Hans-Christian Schmid",
      "initial_release_date": "2003-02-11"
    },
    {
      "name": "Divine Intervention",
      "genre": "Black comedy",
      "directed_by": "Elia Suleiman",
      "initial_release_date": "2002-05-19"
    },
    {
      "name": "DOA: Dead or Alive",
      "genre": "Action Film",
      "directed_by": "Corey Yuen",
      "initial_release_date": "2006-09-07"
    },
    {
      "name": "Dogtown and Z-Boys",
      "genre": "Documentary film",
      "directed_by": "Stacy Peralta",
      "initial_release_date": "2001-01-19"
    },
    {
      "name": "Dogville",
      "genre": "Drama",
      "directed_by": "Lars von Trier",
      "initial_release_date": "2003-05-19"
    },
    {
      "name": "Don: The Chase Begins Again",
      "genre": "Crime Fiction",
      "directed_by": "Farhan Akhtar",
      "initial_release_date": "2006-10-20"
    },
    {
      "name": "Don's Plum",
      "genre": "Black-and-white",
      "directed_by": "R.D. Robb",
      "initial_release_date": "2001-02-10"
    },
    {
      "name": "Dopamine",
      "genre": "Comedy-drama",
      "directed_by": "Mark Decena",
      "initial_release_date": "2003-01-23"
    },
    {
      "name": "Double Take",
      "genre": "Crime Fiction",
      "directed_by": "George Gallo",
      "initial_release_date": "2001-01-12"
    },
    {
      "name": "Double Whammy",
      "genre": "Comedy-drama",
      "directed_by": "Tom DiCillo",
      "initial_release_date": "2001-01-20"
    },
    {
      "name": "Downfall",
      "genre": "Biographical film",
      "directed_by": "Oliver Hirschbiegel",
      "initial_release_date": "2004-09-08"
    },
    {
      "name": "Dragon Boys",
      "genre": "Crime Drama",
      "directed_by": "Jerry Ciccoritti"
    },
    {
      "name": "Dragonlance: Dragons of Autumn Twilight",
      "genre": "Animation",
      "directed_by": "Will Meugniot",
      "initial_release_date": "2008-01-15"
    },
    {
      "name": "Drawing Restraint 9",
      "genre": "Cult film",
      "directed_by": "Matthew Barney",
      "initial_release_date": "2005-07-01"
    },
    {
      "name": "Drowning Mona",
      "genre": "Black comedy",
      "directed_by": "Nick Gomez",
      "initial_release_date": "2000-01-02"
    },
    {
      "name": "Druids",
      "genre": "Adventure Film",
      "directed_by": "Jacques Dorfmann",
      "initial_release_date": "2001-08-31"
    },
    {
      "name": "Dumb &amp; Dumberer: When Harry Met Lloyd",
      "genre": "Buddy film",
      "directed_by": "Troy Miller",
      "initial_release_date": "2003-06-13"
    },
    {
      "name": "Duplex",
      "genre": "Black comedy",
      "directed_by": "Danny DeVito",
      "initial_release_date": "2003-09-26"
    },
    {
      "name": "E",
      "genre": "Action Film",
      "directed_by": "S. P. Jananathan",
      "initial_release_date": "2006-10-21"
    },
    {
      "name": "Earthlings",
      "genre": "Documentary film",
      "directed_by": "Shaun Monson"
    },
    {
      "name": "Eight Below",
      "genre": "Adventure Film",
      "directed_by": "Frank Marshall",
      "initial_release_date": "2006-02-17"
    },
    {
      "name": "Eight Crazy Nights",
      "genre": "Christmas movie",
      "directed_by": "Seth Kearsley",
      "initial_release_date": "2002-11-27"
    },
    {
      "name": "Ek Ajnabee",
      "genre": "Action Film",
      "directed_by": "Apoorva Lakhia",
      "initial_release_date": "2005-12-09"
    },
    {
      "name": "The Archimedes Principle",
      "genre": "Drama",
      "directed_by": "Gerardo Herrero",
      "initial_release_date": "2004-03-26"
    },
    {
      "name": "Election",
      "genre": "Crime Fiction",
      "directed_by": "Johnnie To",
      "initial_release_date": "2005-05-14"
    },
    {
      "name": "Elektra",
      "genre": "Action Film",
      "directed_by": "Rob Bowman",
      "initial_release_date": "2005-01-08"
    },
    {
      "name": "Elvis Has Left the Building",
      "genre": "Action Film",
      "directed_by": "Joel Zwick"
    },
    {
      "name": "Employee of the Month",
      "genre": "Black comedy",
      "directed_by": "Mitch Rouse",
      "initial_release_date": "2004-01-17"
    },
    {
      "name": "Empress Chung",
      "genre": "Animation",
      "directed_by": "Nelson Shin",
      "initial_release_date": "2005-08-12"
    },
    {
      "name": "En Route",
      "genre": "Drama",
      "directed_by": "Jan Krüger",
      "initial_release_date": "2004-06-17"
    },
    {
      "name": "End of the Spear",
      "genre": "Docudrama",
      "directed_by": "Jim Hanon"
    },
    {
      "name": "Enron: The Smartest Guys in the Room",
      "genre": "Documentary film",
      "directed_by": "Alex Gibney",
      "initial_release_date": "2005-04-22"
    },
    {
      "name": "Envy",
      "genre": "Black comedy",
      "directed_by": "Barry Levinson",
      "initial_release_date": "2004-04-30"
    },
    {
      "name": "Erin Brockovich",
      "genre": "Biographical film",
      "directed_by": "Steven Soderbergh",
      "initial_release_date": "2000-03-14"
    },
    {
      "name": "Escaflowne",
      "genre": "Adventure Film",
      "directed_by": "Kazuki Akane",
      "initial_release_date": "2000-06-24"
    },
    {
      "name": "A Few Days Later",
      "genre": "Drama",
      "directed_by": "Niki Karimi"
    },
    {
      "name": "Everyman's Feast",
      "genre": "Drama",
      "directed_by": "Fritz Lehner",
      "initial_release_date": "2002-01-25"
    },
    {
      "name": "Everyone's Hero",
      "genre": "Computer Animation",
      "directed_by": "Christopher Reeve",
      "initial_release_date": "2006-09-15"
    },
    {
      "name": "Everything Is Illuminated",
      "genre": "Adventure Film",
      "directed_by": "Liev Schreiber",
      "initial_release_date": "2005-09-16"
    },
    {
      "name": "Exit Wounds",
      "genre": "Action Film",
      "directed_by": "Andrzej Bartkowiak",
      "initial_release_date": "2001-03-16"
    },
    {
      "name": "Extreme Days",
      "genre": "Comedy-drama",
      "directed_by": "Eric Hannah",
      "initial_release_date": "2001-09-28"
    },
    {
      "name": "Extreme Ops",
      "genre": "Action Film",
      "directed_by": "Christian Duguay",
      "initial_release_date": "2002-11-27"
    },
    {
      "name": "Factory Girl",
      "genre": "Biographical film",
      "directed_by": "George Hickenlooper",
      "initial_release_date": "2006-12-29"
    },
    {
      "name": "Fahrenheit 9/11½",
      "genre": "Documentary film",
      "directed_by": "Michael Moore"
    },
    {
      "name": "Falcons",
      "genre": "Drama",
      "directed_by": "Friðrik Þór Friðriksson"
    },
    {
      "name": "Familywala",
      "genre": "Comedy",
      "directed_by": "Neeraj Vora"
    },
    {
      "name": "Fan Chan",
      "genre": "Comedy",
      "directed_by": "Vitcha Gojiew",
      "initial_release_date": "2003-10-03"
    },
    {
      "name": "Fantastic Mr. Fox",
      "genre": "Animation",
      "directed_by": "Wes Anderson",
      "initial_release_date": "2009-10-14"
    },
    {
      "name": "Far Cry",
      "genre": "Action Film",
      "directed_by": "Uwe Boll",
      "initial_release_date": "2008-10-02"
    },
    {
      "name": "Fat Pizza",
      "genre": "Comedy",
      "directed_by": "Paul Fenech"
    },
    {
      "name": "Fearless",
      "genre": "Biographical film",
      "directed_by": "Ronny Yu",
      "initial_release_date": "2006-01-26"
    },
    {
      "name": "Festival",
      "genre": "Black comedy",
      "directed_by": "Annie Griffin",
      "initial_release_date": "2005-07-15"
    },
    {
      "name": "Festival Express",
      "genre": "Documentary film",
      "directed_by": "Bob Smeaton"
    },
    {
      "name": "Fighter in the Wind",
      "genre": "Action/Adventure",
      "directed_by": "Yang Yun-ho",
      "initial_release_date": "2004-08-06"
    },
    {
      "name": "Filantropica",
      "genre": "Comedy",
      "directed_by": "Nae Caranfil",
      "initial_release_date": "2002-03-15"
    },
    {
      "name": "Final Fantasy VII: Advent Children",
      "genre": "Anime",
      "directed_by": "Tetsuya Nomura",
      "initial_release_date": "2005-08-31"
    },
    {
      "name": "Find Me Guilty",
      "genre": "Crime Fiction",
      "directed_by": "Sidney Lumet",
      "initial_release_date": "2006-02-16"
    },
    {
      "name": "Finding Nemo",
      "genre": "Animation",
      "directed_by": "Andrew Stanton",
      "initial_release_date": "2003-05-30"
    },
    {
      "name": "Finding Neverland",
      "genre": "Costume drama",
      "directed_by": "Marc Forster",
      "initial_release_date": "2004-09-04"
    },
    {
      "name": "First Descent",
      "genre": "Documentary film",
      "directed_by": "Kemp Curly",
      "initial_release_date": "2005-12-02"
    },
    {
      "name": "Flight from Death",
      "genre": "Documentary film",
      "directed_by": "Patrick Shen",
      "initial_release_date": "2006-09-06"
    },
    {
      "name": "Flight of the Phoenix",
      "genre": "Airplanes and airports",
      "directed_by": "John Moore",
      "initial_release_date": "2004-12-17"
    },
    {
      "name": "Flock of Dodos",
      "genre": "Documentary film",
      "directed_by": "Randy Olson"
    },
    {
      "name": "Flushed Away",
      "genre": "Animation",
      "directed_by": "David Bowers",
      "initial_release_date": "2006-10-22"
    },
    {
      "name": "Fool &amp; Final",
      "genre": "Comedy",
      "directed_by": "Ahmed Khan",
      "initial_release_date": "2007-06-01"
    },
    {
      "name": "Foolproof",
      "genre": "Action Film",
      "directed_by": "William Phillips",
      "initial_release_date": "2003-10-03"
    },
    {
      "name": "Four Brothers",
      "genre": "Action Film",
      "directed_by": "John Singleton",
      "initial_release_date": "2005-08-12"
    },
    {
      "name": "Frankenfish",
      "genre": "Action Film",
      "directed_by": "Mark A.Z. Dippé",
      "initial_release_date": "2004-10-09"
    },
    {
      "name": "Free Jimmy",
      "genre": "Anime",
      "directed_by": "Christopher Nielsen",
      "initial_release_date": "2006-04-21"
    },
    {
      "name": "Free Zone",
      "genre": "Comedy",
      "directed_by": "Amos Gitai",
      "initial_release_date": "2005-05-19"
    },
    {
      "name": "Frida",
      "genre": "Biographical film",
      "directed_by": "Julie Taymor",
      "initial_release_date": "2002-08-29"
    },
    {
      "name": "Friday After Next",
      "genre": "Buddy film",
      "directed_by": "Marcus Raboy",
      "initial_release_date": "2002-11-22"
    },
    {
      "name": "Friday Night Lights",
      "genre": "Action Film",
      "directed_by": "Peter Berg",
      "initial_release_date": "2004-10-06"
    },
    {
      "name": "FRO - The Movie",
      "genre": "Comedy-drama",
      "directed_by": "Brad Gashler"
    },
    {
      "name": "Fuck",
      "genre": "Documentary film",
      "directed_by": "Steve Anderson",
      "initial_release_date": "2005-11-07"
    },
    {
      "name": "Fullmetal Alchemist the Movie: Conqueror of Shamballa",
      "genre": "Anime",
      "directed_by": "Seiji Mizushima",
      "initial_release_date": "2005-07-23"
    },
    {
      "name": "Fulltime Killer",
      "genre": "Action Film",
      "directed_by": "Johnnie To",
      "initial_release_date": "2001-08-03"
    },
    {
      "name": "Fun with Dick and Jane",
      "genre": "Crime Fiction",
      "directed_by": "Dean Parisot",
      "initial_release_date": "2005-12-21"
    },
    {
      "name": "Gagamboy",
      "genre": "Action Film",
      "directed_by": "Erik Matti",
      "initial_release_date": "2004-01-01"
    },
    {
      "name": "Gallipoli",
      "genre": "Documentary film",
      "directed_by": "Tolga Örnek",
      "initial_release_date": "2005-03-18"
    },
    {
      "name": "Gangs of New York",
      "genre": "Crime Fiction",
      "directed_by": "Martin Scorsese",
      "initial_release_date": "2002-12-09"
    },
    {
      "name": "Garam Masala",
      "genre": "Comedy",
      "directed_by": "Priyadarshan",
      "initial_release_date": "2005-11-02"
    },
    {
      "name": "George Washington",
      "genre": "Coming of age",
      "directed_by": "David Gordon Green",
      "initial_release_date": "2000-09-29"
    },
    {
      "name": "Georgia Rule",
      "genre": "Comedy-drama",
      "directed_by": "Garry Marshall",
      "initial_release_date": "2007-05-10"
    },
    {
      "name": "Get Rich or Die Tryin'",
      "genre": "Coming of age",
      "directed_by": "Jim Sheridan",
      "initial_release_date": "2005-11-09"
    },
    {
      "name": "Ghost in the Shell: Solid State Society",
      "genre": "Anime",
      "directed_by": "Kenji Kamiyama",
      "initial_release_date": "2006-09-01"
    },
    {
      "name": "Ghost Rider",
      "genre": "Adventure Film",
      "directed_by": "Mark Steven Johnson",
      "initial_release_date": "2007-01-15"
    },
    {
      "name": "Ghosts of Mars",
      "genre": "Adventure Film",
      "directed_by": "John Carpenter",
      "initial_release_date": "2001-08-24"
    },
    {
      "name": "Gie",
      "genre": "Biographical film",
      "directed_by": "Riri Riza",
      "initial_release_date": "2005-07-14"
    },
    {
      "name": "Gigli",
      "genre": "Crime Thriller",
      "directed_by": "Martin Brest",
      "initial_release_date": "2003-07-27"
    },
    {
      "name": "Glastonbury",
      "genre": "Documentary film",
      "directed_by": "Julien Temple",
      "initial_release_date": "2006-04-14"
    },
    {
      "name": "Glastonbury Anthems",
      "genre": "Documentary film",
      "directed_by": "Gavin Taylor"
    },
    {
      "name": "Global Heresy",
      "genre": "Comedy",
      "directed_by": "Sidney J. Furie",
      "initial_release_date": "2002-09-03"
    },
    {
      "name": "God Grew Tired of Us",
      "genre": "Documentary film",
      "directed_by": "Christopher Dillon Quinn",
      "initial_release_date": "2006-09-04"
    },
    {
      "name": "God on My Side",
      "genre": "Documentary film",
      "directed_by": "Andrew Denton",
      "initial_release_date": "2006-11-02"
    },
    {
      "name": "Varalaru",
      "genre": "Action Film",
      "directed_by": "K. S. Ravikumar",
      "initial_release_date": "2006-02-24"
    },
    {
      "name": "Going the Distance",
      "genre": "Comedy",
      "directed_by": "Mark Griffiths",
      "initial_release_date": "2004-08-20"
    },
    {
      "name": "Going Upriver",
      "genre": "Documentary film",
      "directed_by": "George Butler",
      "initial_release_date": "2004-09-14"
    },
    {
      "name": "Goodbye, Dragon Inn",
      "genre": "Comedy-drama",
      "directed_by": "Tsai Ming-liang",
      "initial_release_date": "2003-12-12"
    },
    {
      "name": "Goya's Ghosts",
      "genre": "Biographical film",
      "directed_by": "Miloš Forman",
      "initial_release_date": "2006-11-08"
    },
    {
      "name": "Greenfingers",
      "genre": "Comedy-drama",
      "directed_by": "Joel Hershman",
      "initial_release_date": "2001-09-14"
    },
    {
      "name": "Grill Point",
      "genre": "Drama",
      "directed_by": "Andreas Dresen",
      "initial_release_date": "2002-02-12"
    },
    {
      "name": "Grilled",
      "genre": "Black comedy",
      "directed_by": "Jason Ensler",
      "initial_release_date": "2006-07-11"
    },
    {
      "name": "Grizzly Falls",
      "genre": "Adventure Film",
      "directed_by": "Stewart Raffill",
      "initial_release_date": "2004-06-28"
    },
    {
      "name": "Grizzly Man",
      "genre": "Documentary film",
      "directed_by": "Werner Herzog",
      "initial_release_date": "2005-01-24"
    },
    {
      "name": "GRODMIN",
      "genre": "Avant-garde",
      "directed_by": "Jim Horwitz"
    },
    {
      "name": "Gudumba Shankar",
      "genre": "Action Film",
      "directed_by": "Veera Shankar",
      "initial_release_date": "2004-09-09"
    },
    {
      "name": "Che: Part Two",
      "genre": "Biographical film",
      "directed_by": "Steven Soderbergh",
      "initial_release_date": "2008-05-21"
    },
    {
      "name": "Gunner Palace",
      "genre": "Documentary film",
      "directed_by": "Michael Tucker",
      "initial_release_date": "2005-03-04"
    },
    {
      "name": "Guru",
      "genre": "Biographical film",
      "directed_by": "Mani Ratnam",
      "initial_release_date": "2007-01-12"
    },
    {
      "name": "Gypsy 83",
      "genre": "Coming of age",
      "directed_by": "Todd Stephens"
    },
    {
      "name": "Haiku Tunnel",
      "genre": "Black comedy",
      "directed_by": "Jacob Kornbluth"
    },
    {
      "name": "Making Babies",
      "genre": "Drama",
      "directed_by": "Daniel Lind Lagerlöf",
      "initial_release_date": "2001-01-29"
    },
    {
      "name": "Hanuman",
      "genre": "Animation",
      "directed_by": "V.G. Samant",
      "initial_release_date": "2005-10-21"
    },
    {
      "name": "Hanuman Junction",
      "genre": "Action Film",
      "directed_by": "M.Raja",
      "initial_release_date": "2001-12-21"
    },
    {
      "name": "I Love New Year",
      "genre": "Caper story",
      "directed_by": "Radhika Rao",
      "initial_release_date": "2013-12-30"
    },
    {
      "name": "Harry Potter and the Chamber of Secrets",
      "genre": "Adventure Film",
      "directed_by": "Chris Columbus",
      "initial_release_date": "2002-11-03"
    },
    {
      "name": "Harry Potter and the Half-Blood Prince",
      "genre": "Adventure Film",
      "directed_by": "David Yates",
      "initial_release_date": "2009-07-06"
    },
    {
      "name": "Le Havre",
      "genre": "Drama",
      "directed_by": "Aki Kaurismäki",
      "initial_release_date": "2011"
    }
  ]
}
